{"frameRate":24,"armature":[{"bone":[{"name":"root","transform":{"y":12.2295,"x":0.8612}},{"length":24,"transform":{"y":-106.6295,"skX":-91.5228,"skY":-91.5228,"x":-1.2112},"parent":"root","name":"头_拷贝"},{"length":11,"transform":{"y":-41.1295,"skX":-90.9793,"skY":-90.9793,"x":61.2388},"parent":"root","name":"5"},{"length":9,"transform":{"y":-85.8295,"skX":-87.6141,"skY":-87.6141,"x":23.3388},"parent":"root","name":"2"},{"length":7,"transform":{"y":-38.4795,"skX":-90,"skY":-90,"x":-50.0612},"parent":"root","name":"6"},{"length":5,"transform":{"y":-108.7795,"skX":-90,"skY":-90,"x":-39.0112},"parent":"root","name":"3"},{"length":13,"transform":{"y":-181.0295,"skX":-92.3074,"skY":-92.3074,"x":-32.5612},"parent":"root","name":"1"},{"length":7,"transform":{"y":-162.4795,"skX":-90,"skY":-90,"x":50.4888},"parent":"root","name":"4"}],"ik":[],"type":"Armature","name":"armatureName","slot":[{"color":{},"name":"头_拷贝","parent":"头_拷贝"},{"z":1,"color":{},"name":"6","parent":"6"},{"z":2,"color":{},"name":"5","parent":"5"},{"z":3,"color":{},"name":"4","parent":"4"},{"z":4,"color":{},"name":"3","parent":"3"},{"z":5,"color":{},"name":"2","parent":"2"},{"z":6,"color":{},"name":"1","parent":"1"}],"skin":[{"name":"","slot":[{"display":[{"path":"1","type":"image","name":"1","transform":{"y":-0.0208,"skX":92.3074,"skY":92.3074,"x":3.2958}}],"name":"1"},{"display":[{"path":"头_拷贝","type":"image","name":"头_拷贝","transform":{"y":-0.1711,"skX":91.5228,"skY":91.5228,"x":-6.3054}}],"name":"头_拷贝"},{"display":[{"path":"2","type":"image","name":"2","transform":{"y":1.3207,"skX":87.6141,"skY":87.6141,"x":3.0499}}],"name":"2"},{"display":[{"path":"6","type":"image","name":"6","transform":{"y":0.8465,"skX":90,"skY":90,"x":1.3423}}],"name":"6"},{"display":[{"path":"5","type":"image","name":"5","transform":{"y":1.118,"skX":90.9793,"skY":90.9793,"x":4.1738}}],"name":"5"},{"display":[{"path":"4","type":"image","name":"4","transform":{"y":0.7965,"skX":90,"skY":90,"x":2.8423}}],"name":"4"},{"display":[{"path":"3","type":"image","name":"3","transform":{"y":0.2965,"skX":90,"skY":90,"x":1.5423}}],"name":"3"}]}],"aabb":{"width":154,"y":-191.5922900435288,"height":191.00000000000006,"x":-64.35351036465609},"frameRate":24,"defaultActions":[{"gotoAndPlay":"flash"}],"animation":[{"bone":[{"frame":[{"transform":{},"duration":24}],"name":"root"},{"frame":[{"transform":{},"duration":24}],"name":"头_拷贝"},{"frame":[{"transform":{},"duration":24}],"name":"5"},{"frame":[{"transform":{},"duration":24}],"name":"2"},{"frame":[{"transform":{},"duration":24}],"name":"6"},{"frame":[{"transform":{},"duration":24}],"name":"3"},{"frame":[{"transform":{},"duration":24}],"name":"1"},{"frame":[{"transform":{},"duration":24}],"name":"4"}],"frame":[],"ik":[],"playTimes":0,"slot":[{"frame":[{"tweenEasing":0,"duration":12},{"tweenEasing":0,"duration":12,"color":{"aM":0}},{"tweenEasing":null,"duration":0}],"name":"6"},{"frame":[{"tweenEasing":0,"duration":10,"color":{"aM":0}},{"tweenEasing":0,"duration":8},{"tweenEasing":null,"duration":6,"color":{"aM":0}}],"name":"5"},{"frame":[{"tweenEasing":0,"duration":13},{"tweenEasing":0,"duration":11,"color":{"aM":0}},{"tweenEasing":null,"duration":0}],"name":"4"},{"frame":[{"tweenEasing":0,"duration":9,"color":{"aM":0}},{"tweenEasing":0,"duration":8,"color":{"aM":0}},{"tweenEasing":0,"duration":6},{"tweenEasing":null,"duration":1,"color":{"aM":0}}],"name":"3"},{"frame":[{"tweenEasing":0,"duration":7,"color":{"aM":0}},{"tweenEasing":0,"duration":8,"color":{"aM":0}},{"tweenEasing":0,"duration":9},{"tweenEasing":null,"duration":0,"color":{"aM":0}}],"name":"2"},{"frame":[{"tweenEasing":0,"duration":13,"color":{"aM":0}},{"tweenEasing":0,"duration":11},{"tweenEasing":null,"duration":0,"color":{"aM":0}}],"name":"1"}],"duration":24,"name":"flash","ffd":[]}]},{"bone":[{"name":"root","transform":{}}],"ik":[],"type":"Armature","name":"armatureName1","slot":[{"color":{},"name":"头_拷贝","parent":"root"},{"z":1,"color":{},"name":"6","parent":"root"},{"z":2,"color":{},"name":"5","parent":"root"},{"z":3,"color":{},"name":"4","parent":"root"},{"z":4,"color":{},"name":"3","parent":"root"},{"z":5,"color":{},"name":"2","parent":"root"},{"z":6,"color":{},"name":"1","parent":"root"}],"skin":[{"name":"","slot":[{"display":[{"path":"2","type":"image","name":"2","transform":{"y":338,"x":-22}}],"name":"2"},{"display":[{"path":"3","type":"image","name":"3","transform":{"y":316.5,"x":-85.5}}],"name":"3"},{"display":[{"path":"4","type":"image","name":"4","transform":{"y":261.5,"x":4.5}}],"name":"4"},{"display":[{"path":"5","type":"image","name":"5","transform":{"y":381.5,"x":15.5}}],"name":"5"},{"display":[{"path":"头_拷贝","type":"image","name":"头_拷贝","transform":{"y":326.5,"x":-48}}],"name":"头_拷贝"},{"display":[{"path":"6","type":"image","name":"6","transform":{"y":387,"x":-96}}],"name":"6"},{"display":[{"path":"1","type":"image","name":"1","transform":{"y":242.5,"x":-79.5}}],"name":"1"}]}],"aabb":{"width":154,"y":223,"height":191,"x":-112},"frameRate":24,"defaultActions":[{"gotoAndPlay":""}],"animation":[]}],"name":"flash","version":"4.0","isGlobal":0}